[
  {
    "_id": "48421230-1733-11e7-b973-af55f23595f6",
    "_type": "dashboard",
    "_source": {
      "title": "nodes",
      "hits": 0,
      "description": "",
      "panelsJSON": "[{\"size_x\":6,\"size_y\":3,\"panelIndex\":1,\"type\":\"visualization\",\"id\":\"16a4f5d0-1733-11e7-b973-af55f23595f6\",\"col\":1,\"row\":1},{\"size_x\":6,\"size_y\":3,\"panelIndex\":2,\"type\":\"visualization\",\"id\":\"d4b47790-1732-11e7-b973-af55f23595f6\",\"col\":7,\"row\":1},{\"size_x\":6,\"size_y\":3,\"panelIndex\":3,\"type\":\"visualization\",\"id\":\"eef1b0f0-1732-11e7-b973-af55f23595f6\",\"col\":1,\"row\":4},{\"size_x\":6,\"size_y\":3,\"panelIndex\":4,\"type\":\"visualization\",\"id\":\"02785160-1733-11e7-b973-af55f23595f6\",\"col\":7,\"row\":4}]",
      "optionsJSON": "{\"darkTheme\":false}",
      "uiStateJSON": "{}",
      "version": 1,
      "timeRestore": false,
      "kibanaSavedObjectMeta": {
        "searchSourceJSON": "{\"filter\":[{\"query\":{\"query_string\":{\"query\":\"*\",\"analyze_wildcard\":true}}}]}"
      }
    }
  },
  {
    "_id": "a925f450-1732-11e7-b973-af55f23595f6",
    "_type": "dashboard",
    "_source": {
      "title": "global",
      "hits": 0,
      "description": "",
      "panelsJSON": "[{\"col\":1,\"id\":\"0063db30-1731-11e7-b973-af55f23595f6\",\"panelIndex\":1,\"row\":1,\"size_x\":6,\"size_y\":3,\"type\":\"visualization\"},{\"col\":7,\"id\":\"f8564850-1731-11e7-b973-af55f23595f6\",\"panelIndex\":2,\"row\":4,\"size_x\":6,\"size_y\":3,\"type\":\"visualization\"},{\"col\":1,\"id\":\"70161af0-1732-11e7-b973-af55f23595f6\",\"panelIndex\":3,\"row\":4,\"size_x\":6,\"size_y\":3,\"type\":\"visualization\"},{\"col\":7,\"id\":\"90a38a50-1732-11e7-b973-af55f23595f6\",\"panelIndex\":4,\"row\":1,\"size_x\":6,\"size_y\":3,\"type\":\"visualization\"}]",
      "optionsJSON": "{\"darkTheme\":true}",
      "uiStateJSON": "{}",
      "version": 1,
      "timeRestore": false,
      "kibanaSavedObjectMeta": {
        "searchSourceJSON": "{\"filter\":[{\"query\":{\"query_string\":{\"analyze_wildcard\":true,\"query\":\"*\"}}}]}"
      }
    }
  },
  {
    "_id": "2a0ad260-1734-11e7-b973-af55f23595f6",
    "_type": "dashboard",
    "_source": {
      "title": "services",
      "hits": 0,
      "description": "",
      "panelsJSON": "[{\"size_x\":6,\"size_y\":3,\"panelIndex\":1,\"type\":\"visualization\",\"id\":\"b9a8fc40-1733-11e7-b973-af55f23595f6\",\"col\":1,\"row\":1},{\"size_x\":6,\"size_y\":3,\"panelIndex\":2,\"type\":\"visualization\",\"id\":\"a33ec3e0-1733-11e7-b973-af55f23595f6\",\"col\":7,\"row\":1},{\"size_x\":6,\"size_y\":3,\"panelIndex\":3,\"type\":\"visualization\",\"id\":\"d9991a30-1733-11e7-b973-af55f23595f6\",\"col\":1,\"row\":4},{\"size_x\":6,\"size_y\":3,\"panelIndex\":4,\"type\":\"visualization\",\"id\":\"caa659c0-1733-11e7-b973-af55f23595f6\",\"col\":7,\"row\":4}]",
      "optionsJSON": "{\"darkTheme\":false}",
      "uiStateJSON": "{}",
      "version": 1,
      "timeRestore": false,
      "kibanaSavedObjectMeta": {
        "searchSourceJSON": "{\"filter\":[{\"query\":{\"query_string\":{\"query\":\"*\",\"analyze_wildcard\":true}}}]}"
      }
    }
  },
  {
    "_id": "67556f40-1734-11e7-b973-af55f23595f6",
    "_type": "dashboard",
    "_source": {
      "title": "stacks",
      "hits": 0,
      "description": "",
      "panelsJSON": "[{\"col\":1,\"id\":\"fa514310-1733-11e7-b973-af55f23595f6\",\"panelIndex\":1,\"row\":1,\"size_x\":6,\"size_y\":3,\"type\":\"visualization\"},{\"size_x\":6,\"size_y\":3,\"panelIndex\":2,\"type\":\"visualization\",\"id\":\"5791ca40-1734-11e7-b973-af55f23595f6\",\"col\":7,\"row\":1},{\"size_x\":6,\"size_y\":3,\"panelIndex\":3,\"type\":\"visualization\",\"id\":\"e6491690-1733-11e7-b973-af55f23595f6\",\"col\":1,\"row\":4},{\"size_x\":6,\"size_y\":3,\"panelIndex\":4,\"type\":\"visualization\",\"id\":\"078def10-1734-11e7-b973-af55f23595f6\",\"col\":7,\"row\":4}]",
      "optionsJSON": "{\"darkTheme\":false}",
      "uiStateJSON": "{}",
      "version": 1,
      "timeRestore": false,
      "kibanaSavedObjectMeta": {
        "searchSourceJSON": "{\"filter\":[{\"query\":{\"query_string\":{\"analyze_wildcard\":true,\"query\":\"*\"}}}]}"
      }
    }
  },
  {
    "_id": "eef1b0f0-1732-11e7-b973-af55f23595f6",
    "_type": "visualization",
    "_source": {
      "title": "net_nodes",
      "visState": "{\"title\":\"net_nodes\",\"type\":\"line\",\"params\":{\"addLegend\":true,\"addTimeMarker\":false,\"addTooltip\":true,\"defaultYExtents\":false,\"drawLinesBetweenPoints\":true,\"interpolate\":\"linear\",\"legendPosition\":\"right\",\"radiusRatio\":9,\"scale\":\"linear\",\"setYExtents\":false,\"showCircles\":true,\"times\":[]},\"aggs\":[{\"id\":\"2\",\"enabled\":true,\"type\":\"date_histogram\",\"schema\":\"segment\",\"params\":{\"field\":\"@timestamp\",\"interval\":\"auto\",\"customInterval\":\"2h\",\"min_doc_count\":1,\"extended_bounds\":{}}},{\"id\":\"3\",\"enabled\":true,\"type\":\"avg\",\"schema\":\"metric\",\"params\":{\"field\":\"net.totalBytes\"}},{\"id\":\"4\",\"enabled\":true,\"type\":\"terms\",\"schema\":\"group\",\"params\":{\"field\":\"node_id\",\"size\":5,\"order\":\"desc\",\"orderBy\":\"3\"}}],\"listeners\":{}}",
      "uiStateJSON": "{}",
      "description": "",
      "version": 1,
      "kibanaSavedObjectMeta": {
        "searchSourceJSON": "{\"index\":\"ampbeat-*\",\"query\":{\"query_string\":{\"analyze_wildcard\":true,\"query\":\"*\"}},\"filter\":[]}"
      }
    }
  },
  {
    "_id": "ded16d00-1732-11e7-b973-af55f23595f6",
    "_type": "visualization",
    "_source": {
      "title": "net_nodes",
      "visState": "{\"title\":\"net_nodes\",\"type\":\"line\",\"params\":{\"addLegend\":true,\"addTimeMarker\":false,\"addTooltip\":true,\"defaultYExtents\":false,\"drawLinesBetweenPoints\":true,\"interpolate\":\"linear\",\"legendPosition\":\"right\",\"radiusRatio\":9,\"scale\":\"linear\",\"setYExtents\":false,\"showCircles\":true,\"times\":[]},\"aggs\":[{\"id\":\"2\",\"enabled\":true,\"type\":\"date_histogram\",\"schema\":\"segment\",\"params\":{\"field\":\"@timestamp\",\"interval\":\"auto\",\"customInterval\":\"2h\",\"min_doc_count\":1,\"extended_bounds\":{}}},{\"id\":\"3\",\"enabled\":true,\"type\":\"avg\",\"schema\":\"metric\",\"params\":{\"field\":\"mem.usage\"}},{\"id\":\"4\",\"enabled\":true,\"type\":\"terms\",\"schema\":\"group\",\"params\":{\"field\":\"node_id\",\"size\":5,\"order\":\"desc\",\"orderBy\":\"3\"}}],\"listeners\":{}}",
      "uiStateJSON": "{}",
      "description": "",
      "version": 1,
      "kibanaSavedObjectMeta": {
        "searchSourceJSON": "{\"index\":\"ampbeat-*\",\"query\":{\"query_string\":{\"analyze_wildcard\":true,\"query\":\"*\"}},\"filter\":[]}"
      }
    }
  },
  {
    "_id": "02785160-1733-11e7-b973-af55f23595f6",
    "_type": "visualization",
    "_source": {
      "title": "io_nodes",
      "visState": "{\"title\":\"io_nodes\",\"type\":\"line\",\"params\":{\"addLegend\":true,\"addTimeMarker\":false,\"addTooltip\":true,\"defaultYExtents\":false,\"drawLinesBetweenPoints\":true,\"interpolate\":\"linear\",\"legendPosition\":\"right\",\"radiusRatio\":9,\"scale\":\"linear\",\"setYExtents\":false,\"showCircles\":true,\"times\":[]},\"aggs\":[{\"id\":\"2\",\"enabled\":true,\"type\":\"date_histogram\",\"schema\":\"segment\",\"params\":{\"field\":\"@timestamp\",\"interval\":\"auto\",\"customInterval\":\"2h\",\"min_doc_count\":1,\"extended_bounds\":{}}},{\"id\":\"3\",\"enabled\":true,\"type\":\"avg\",\"schema\":\"metric\",\"params\":{\"field\":\"io.total\"}},{\"id\":\"4\",\"enabled\":true,\"type\":\"terms\",\"schema\":\"group\",\"params\":{\"field\":\"node_id\",\"size\":5,\"order\":\"desc\",\"orderBy\":\"3\"}}],\"listeners\":{}}",
      "uiStateJSON": "{}",
      "description": "",
      "version": 1,
      "kibanaSavedObjectMeta": {
        "searchSourceJSON": "{\"index\":\"ampbeat-*\",\"query\":{\"query_string\":{\"analyze_wildcard\":true,\"query\":\"*\"}},\"filter\":[]}"
      }
    }
  },
  {
    "_id": "70161af0-1732-11e7-b973-af55f23595f6",
    "_type": "visualization",
    "_source": {
      "title": "net_global",
      "visState": "{\"aggs\":[{\"enabled\":true,\"id\":\"2\",\"params\":{\"customInterval\":\"2h\",\"extended_bounds\":{},\"field\":\"@timestamp\",\"interval\":\"auto\",\"min_doc_count\":1},\"schema\":\"segment\",\"type\":\"date_histogram\"},{\"enabled\":true,\"id\":\"3\",\"params\":{\"field\":\"io.total\"},\"schema\":\"metric\",\"type\":\"avg\"}],\"listeners\":{},\"params\":{\"addLegend\":true,\"addTimeMarker\":false,\"addTooltip\":true,\"defaultYExtents\":false,\"drawLinesBetweenPoints\":true,\"interpolate\":\"linear\",\"legendPosition\":\"right\",\"radiusRatio\":9,\"scale\":\"linear\",\"setYExtents\":false,\"showCircles\":true,\"times\":[]},\"title\":\"net_global\",\"type\":\"line\"}",
      "uiStateJSON": "{}",
      "description": "",
      "version": 1,
      "kibanaSavedObjectMeta": {
        "searchSourceJSON": "{\"index\":\"ampbeat-*\",\"query\":{\"query_string\":{\"analyze_wildcard\":true,\"query\":\"*\"}},\"filter\":[]}"
      }
    }
  },
  {
    "_id": "90a38a50-1732-11e7-b973-af55f23595f6",
    "_type": "visualization",
    "_source": {
      "title": "mem_global",
      "visState": "{\"title\":\"mem_global\",\"type\":\"line\",\"params\":{\"addLegend\":true,\"addTimeMarker\":false,\"addTooltip\":true,\"defaultYExtents\":false,\"drawLinesBetweenPoints\":true,\"interpolate\":\"linear\",\"legendPosition\":\"right\",\"radiusRatio\":9,\"scale\":\"linear\",\"setYExtents\":false,\"showCircles\":true,\"times\":[]},\"aggs\":[{\"id\":\"2\",\"enabled\":true,\"type\":\"date_histogram\",\"schema\":\"segment\",\"params\":{\"field\":\"@timestamp\",\"interval\":\"auto\",\"customInterval\":\"2h\",\"min_doc_count\":1,\"extended_bounds\":{}}},{\"id\":\"3\",\"enabled\":true,\"type\":\"avg\",\"schema\":\"metric\",\"params\":{\"field\":\"mem.usage\"}}],\"listeners\":{}}",
      "uiStateJSON": "{}",
      "description": "",
      "version": 1,
      "kibanaSavedObjectMeta": {
        "searchSourceJSON": "{\"index\":\"ampbeat-*\",\"query\":{\"query_string\":{\"analyze_wildcard\":true,\"query\":\"*\"}},\"filter\":[]}"
      }
    }
  },
  {
    "_id": "f8564850-1731-11e7-b973-af55f23595f6",
    "_type": "visualization",
    "_source": {
      "title": "io_global",
      "visState": "{\"title\":\"io_global\",\"type\":\"line\",\"params\":{\"addLegend\":true,\"addTimeMarker\":false,\"addTooltip\":true,\"defaultYExtents\":false,\"drawLinesBetweenPoints\":true,\"interpolate\":\"linear\",\"legendPosition\":\"right\",\"radiusRatio\":9,\"scale\":\"linear\",\"setYExtents\":false,\"showCircles\":true,\"times\":[]},\"aggs\":[{\"id\":\"2\",\"enabled\":true,\"type\":\"date_histogram\",\"schema\":\"segment\",\"params\":{\"field\":\"@timestamp\",\"interval\":\"auto\",\"customInterval\":\"2h\",\"min_doc_count\":1,\"extended_bounds\":{}}},{\"id\":\"3\",\"enabled\":true,\"type\":\"avg\",\"schema\":\"metric\",\"params\":{\"field\":\"io.total\"}}],\"listeners\":{}}",
      "uiStateJSON": "{}",
      "description": "",
      "version": 1,
      "kibanaSavedObjectMeta": {
        "searchSourceJSON": "{\"index\":\"ampbeat-*\",\"query\":{\"query_string\":{\"analyze_wildcard\":true,\"query\":\"*\"}},\"filter\":[]}"
      }
    }
  },
  {
    "_id": "0063db30-1731-11e7-b973-af55f23595f6",
    "_type": "visualization",
    "_source": {
      "title": "cpu_global",
      "visState": "{\"title\":\"cpu_global\",\"type\":\"line\",\"params\":{\"addTooltip\":true,\"addLegend\":true,\"legendPosition\":\"right\",\"showCircles\":true,\"interpolate\":\"linear\",\"scale\":\"linear\",\"drawLinesBetweenPoints\":true,\"radiusRatio\":9,\"times\":[],\"addTimeMarker\":false,\"defaultYExtents\":false,\"setYExtents\":false},\"aggs\":[{\"id\":\"1\",\"enabled\":true,\"type\":\"count\",\"schema\":\"metric\",\"params\":{}},{\"id\":\"3\",\"enabled\":true,\"type\":\"date_histogram\",\"schema\":\"segment\",\"params\":{\"field\":\"@timestamp\",\"interval\":\"auto\",\"customInterval\":\"2h\",\"min_doc_count\":1,\"extended_bounds\":{}}}],\"listeners\":{}}",
      "uiStateJSON": "{}",
      "description": "",
      "version": 1,
      "kibanaSavedObjectMeta": {
        "searchSourceJSON": "{\"index\":\"ampbeat-*\",\"query\":{\"query_string\":{\"query\":\"*\",\"analyze_wildcard\":true}},\"filter\":[]}"
      }
    }
  },
  {
    "_id": "b9a8fc40-1733-11e7-b973-af55f23595f6",
    "_type": "visualization",
    "_source": {
      "title": "cpu_services",
      "visState": "{\"title\":\"cpu_services\",\"type\":\"line\",\"params\":{\"addLegend\":true,\"addTimeMarker\":false,\"addTooltip\":true,\"defaultYExtents\":false,\"drawLinesBetweenPoints\":true,\"interpolate\":\"linear\",\"legendPosition\":\"right\",\"radiusRatio\":9,\"scale\":\"linear\",\"setYExtents\":false,\"showCircles\":true,\"times\":[]},\"aggs\":[{\"id\":\"2\",\"enabled\":true,\"type\":\"date_histogram\",\"schema\":\"segment\",\"params\":{\"field\":\"@timestamp\",\"interval\":\"auto\",\"customInterval\":\"2h\",\"min_doc_count\":1,\"extended_bounds\":{}}},{\"id\":\"3\",\"enabled\":true,\"type\":\"sum\",\"schema\":\"metric\",\"params\":{\"field\":\"cpu.totalUsage\"}},{\"id\":\"4\",\"enabled\":true,\"type\":\"terms\",\"schema\":\"group\",\"params\":{\"field\":\"service_name\",\"size\":5,\"order\":\"desc\",\"orderBy\":\"3\"}}],\"listeners\":{}}",
      "uiStateJSON": "{}",
      "description": "",
      "version": 1,
      "kibanaSavedObjectMeta": {
        "searchSourceJSON": "{\"index\":\"ampbeat-*\",\"query\":{\"query_string\":{\"analyze_wildcard\":true,\"query\":\"*\"}},\"filter\":[]}"
      }
    }
  },
  {
    "_id": "d9991a30-1733-11e7-b973-af55f23595f6",
    "_type": "visualization",
    "_source": {
      "title": "net_services",
      "visState": "{\"title\":\"net_services\",\"type\":\"line\",\"params\":{\"addLegend\":true,\"addTimeMarker\":false,\"addTooltip\":true,\"defaultYExtents\":false,\"drawLinesBetweenPoints\":true,\"interpolate\":\"linear\",\"legendPosition\":\"right\",\"radiusRatio\":9,\"scale\":\"linear\",\"setYExtents\":false,\"showCircles\":true,\"times\":[]},\"aggs\":[{\"id\":\"2\",\"enabled\":true,\"type\":\"date_histogram\",\"schema\":\"segment\",\"params\":{\"field\":\"@timestamp\",\"interval\":\"auto\",\"customInterval\":\"2h\",\"min_doc_count\":1,\"extended_bounds\":{}}},{\"id\":\"3\",\"enabled\":true,\"type\":\"avg\",\"schema\":\"metric\",\"params\":{\"field\":\"mem.usage\"}},{\"id\":\"4\",\"enabled\":true,\"type\":\"terms\",\"schema\":\"group\",\"params\":{\"field\":\"service_name\",\"size\":5,\"order\":\"desc\",\"orderBy\":\"3\"}}],\"listeners\":{}}",
      "uiStateJSON": "{}",
      "description": "",
      "version": 1,
      "kibanaSavedObjectMeta": {
        "searchSourceJSON": "{\"index\":\"ampbeat-*\",\"query\":{\"query_string\":{\"analyze_wildcard\":true,\"query\":\"*\"}},\"filter\":[]}"
      }
    }
  },
  {
    "_id": "caa659c0-1733-11e7-b973-af55f23595f6",
    "_type": "visualization",
    "_source": {
      "title": "io_services",
      "visState": "{\"title\":\"io_services\",\"type\":\"line\",\"params\":{\"addLegend\":true,\"addTimeMarker\":false,\"addTooltip\":true,\"defaultYExtents\":false,\"drawLinesBetweenPoints\":true,\"interpolate\":\"linear\",\"legendPosition\":\"right\",\"radiusRatio\":9,\"scale\":\"linear\",\"setYExtents\":false,\"showCircles\":true,\"times\":[]},\"aggs\":[{\"id\":\"2\",\"enabled\":true,\"type\":\"date_histogram\",\"schema\":\"segment\",\"params\":{\"field\":\"@timestamp\",\"interval\":\"auto\",\"customInterval\":\"2h\",\"min_doc_count\":1,\"extended_bounds\":{}}},{\"id\":\"3\",\"enabled\":true,\"type\":\"avg\",\"schema\":\"metric\",\"params\":{\"field\":\"io.total\"}},{\"id\":\"4\",\"enabled\":true,\"type\":\"terms\",\"schema\":\"group\",\"params\":{\"field\":\"service_name\",\"size\":5,\"order\":\"desc\",\"orderBy\":\"3\"}}],\"listeners\":{}}",
      "uiStateJSON": "{}",
      "description": "",
      "version": 1,
      "kibanaSavedObjectMeta": {
        "searchSourceJSON": "{\"index\":\"ampbeat-*\",\"query\":{\"query_string\":{\"analyze_wildcard\":true,\"query\":\"*\"}},\"filter\":[]}"
      }
    }
  },
  {
    "_id": "e6491690-1733-11e7-b973-af55f23595f6",
    "_type": "visualization",
    "_source": {
      "title": "net_stacks",
      "visState": "{\"title\":\"net_stacks\",\"type\":\"line\",\"params\":{\"addLegend\":true,\"addTimeMarker\":false,\"addTooltip\":true,\"defaultYExtents\":false,\"drawLinesBetweenPoints\":true,\"interpolate\":\"linear\",\"legendPosition\":\"right\",\"radiusRatio\":9,\"scale\":\"linear\",\"setYExtents\":false,\"showCircles\":true,\"times\":[]},\"aggs\":[{\"id\":\"2\",\"enabled\":true,\"type\":\"date_histogram\",\"schema\":\"segment\",\"params\":{\"field\":\"@timestamp\",\"interval\":\"auto\",\"customInterval\":\"2h\",\"min_doc_count\":1,\"extended_bounds\":{}}},{\"id\":\"3\",\"enabled\":true,\"type\":\"avg\",\"schema\":\"metric\",\"params\":{\"field\":\"mem.usage\"}},{\"id\":\"4\",\"enabled\":true,\"type\":\"terms\",\"schema\":\"group\",\"params\":{\"field\":\"stack_name\",\"size\":5,\"order\":\"desc\",\"orderBy\":\"3\"}}],\"listeners\":{}}",
      "uiStateJSON": "{}",
      "description": "",
      "version": 1,
      "kibanaSavedObjectMeta": {
        "searchSourceJSON": "{\"index\":\"ampbeat-*\",\"query\":{\"query_string\":{\"analyze_wildcard\":true,\"query\":\"*\"}},\"filter\":[]}"
      }
    }
  },
  {
    "_id": "16a4f5d0-1733-11e7-b973-af55f23595f6",
    "_type": "visualization",
    "_source": {
      "title": "cpu_nodes",
      "visState": "{\"title\":\"cpu_nodes\",\"type\":\"line\",\"params\":{\"addLegend\":true,\"addTimeMarker\":false,\"addTooltip\":true,\"defaultYExtents\":false,\"drawLinesBetweenPoints\":true,\"interpolate\":\"linear\",\"legendPosition\":\"right\",\"radiusRatio\":9,\"scale\":\"linear\",\"setYExtents\":false,\"showCircles\":true,\"times\":[]},\"aggs\":[{\"id\":\"2\",\"enabled\":true,\"type\":\"date_histogram\",\"schema\":\"segment\",\"params\":{\"field\":\"@timestamp\",\"interval\":\"auto\",\"customInterval\":\"2h\",\"min_doc_count\":1,\"extended_bounds\":{}}},{\"id\":\"3\",\"enabled\":true,\"type\":\"sum\",\"schema\":\"metric\",\"params\":{\"field\":\"cpu.totalUsage\"}},{\"id\":\"4\",\"enabled\":true,\"type\":\"terms\",\"schema\":\"group\",\"params\":{\"field\":\"node_id\",\"size\":5,\"order\":\"desc\",\"orderBy\":\"3\"}}],\"listeners\":{}}",
      "uiStateJSON": "{}",
      "description": "",
      "version": 1,
      "kibanaSavedObjectMeta": {
        "searchSourceJSON": "{\"index\":\"ampbeat-*\",\"query\":{\"query_string\":{\"analyze_wildcard\":true,\"query\":\"*\"}},\"filter\":[]}"
      }
    }
  },
  {
    "_id": "d4b47790-1732-11e7-b973-af55f23595f6",
    "_type": "visualization",
    "_source": {
      "title": "mem_nodes",
      "visState": "{\"title\":\"mem_nodes\",\"type\":\"line\",\"params\":{\"addLegend\":true,\"addTimeMarker\":false,\"addTooltip\":true,\"defaultYExtents\":false,\"drawLinesBetweenPoints\":true,\"interpolate\":\"linear\",\"legendPosition\":\"right\",\"radiusRatio\":9,\"scale\":\"linear\",\"setYExtents\":false,\"showCircles\":true,\"times\":[]},\"aggs\":[{\"id\":\"2\",\"enabled\":true,\"type\":\"date_histogram\",\"schema\":\"segment\",\"params\":{\"field\":\"@timestamp\",\"interval\":\"auto\",\"customInterval\":\"2h\",\"min_doc_count\":1,\"extended_bounds\":{}}},{\"id\":\"3\",\"enabled\":true,\"type\":\"avg\",\"schema\":\"metric\",\"params\":{\"field\":\"mem.usage\"}},{\"id\":\"4\",\"enabled\":true,\"type\":\"terms\",\"schema\":\"group\",\"params\":{\"field\":\"node_id\",\"size\":5,\"order\":\"desc\",\"orderBy\":\"3\"}}],\"listeners\":{}}",
      "uiStateJSON": "{}",
      "description": "",
      "version": 1,
      "kibanaSavedObjectMeta": {
        "searchSourceJSON": "{\"index\":\"ampbeat-*\",\"query\":{\"query_string\":{\"analyze_wildcard\":true,\"query\":\"*\"}},\"filter\":[]}"
      }
    }
  },
  {
    "_id": "fa514310-1733-11e7-b973-af55f23595f6",
    "_type": "visualization",
    "_source": {
      "title": "cpu_stacks",
      "visState": "{\"title\":\"cpu_stacks\",\"type\":\"line\",\"params\":{\"addLegend\":true,\"addTimeMarker\":false,\"addTooltip\":true,\"defaultYExtents\":false,\"drawLinesBetweenPoints\":true,\"interpolate\":\"linear\",\"legendPosition\":\"right\",\"radiusRatio\":9,\"scale\":\"linear\",\"setYExtents\":false,\"showCircles\":true,\"times\":[]},\"aggs\":[{\"id\":\"2\",\"enabled\":true,\"type\":\"date_histogram\",\"schema\":\"segment\",\"params\":{\"field\":\"@timestamp\",\"interval\":\"auto\",\"customInterval\":\"2h\",\"min_doc_count\":1,\"extended_bounds\":{}}},{\"id\":\"3\",\"enabled\":true,\"type\":\"sum\",\"schema\":\"metric\",\"params\":{\"field\":\"cpu.totalUsage\"}},{\"id\":\"4\",\"enabled\":true,\"type\":\"terms\",\"schema\":\"group\",\"params\":{\"field\":\"stack_name\",\"size\":5,\"order\":\"desc\",\"orderBy\":\"3\"}}],\"listeners\":{}}",
      "uiStateJSON": "{}",
      "description": "",
      "version": 1,
      "kibanaSavedObjectMeta": {
        "searchSourceJSON": "{\"index\":\"ampbeat-*\",\"query\":{\"query_string\":{\"analyze_wildcard\":true,\"query\":\"*\"}},\"filter\":[]}"
      }
    }
  },
  {
    "_id": "078def10-1734-11e7-b973-af55f23595f6",
    "_type": "visualization",
    "_source": {
      "title": "io_stacks",
      "visState": "{\"title\":\"io_stacks\",\"type\":\"line\",\"params\":{\"addLegend\":true,\"addTimeMarker\":false,\"addTooltip\":true,\"defaultYExtents\":false,\"drawLinesBetweenPoints\":true,\"interpolate\":\"linear\",\"legendPosition\":\"right\",\"radiusRatio\":9,\"scale\":\"linear\",\"setYExtents\":false,\"showCircles\":true,\"times\":[]},\"aggs\":[{\"id\":\"2\",\"enabled\":true,\"type\":\"date_histogram\",\"schema\":\"segment\",\"params\":{\"field\":\"@timestamp\",\"interval\":\"auto\",\"customInterval\":\"2h\",\"min_doc_count\":1,\"extended_bounds\":{}}},{\"id\":\"3\",\"enabled\":true,\"type\":\"avg\",\"schema\":\"metric\",\"params\":{\"field\":\"io.total\"}},{\"id\":\"4\",\"enabled\":true,\"type\":\"terms\",\"schema\":\"group\",\"params\":{\"field\":\"stack_name\",\"size\":5,\"order\":\"desc\",\"orderBy\":\"3\"}}],\"listeners\":{}}",
      "uiStateJSON": "{}",
      "description": "",
      "version": 1,
      "kibanaSavedObjectMeta": {
        "searchSourceJSON": "{\"index\":\"ampbeat-*\",\"query\":{\"query_string\":{\"analyze_wildcard\":true,\"query\":\"*\"}},\"filter\":[]}"
      }
    }
  },
  {
    "_id": "161ee070-1734-11e7-b973-af55f23595f6",
    "_type": "visualization",
    "_source": {
      "title": "net_stacks",
      "visState": "{\"title\":\"net_stacks\",\"type\":\"line\",\"params\":{\"addLegend\":true,\"addTimeMarker\":false,\"addTooltip\":true,\"defaultYExtents\":false,\"drawLinesBetweenPoints\":true,\"interpolate\":\"linear\",\"legendPosition\":\"right\",\"radiusRatio\":9,\"scale\":\"linear\",\"setYExtents\":false,\"showCircles\":true,\"times\":[]},\"aggs\":[{\"id\":\"2\",\"enabled\":true,\"type\":\"date_histogram\",\"schema\":\"segment\",\"params\":{\"field\":\"@timestamp\",\"interval\":\"auto\",\"customInterval\":\"2h\",\"min_doc_count\":1,\"extended_bounds\":{}}},{\"id\":\"3\",\"enabled\":true,\"type\":\"avg\",\"schema\":\"metric\",\"params\":{\"field\":\"mem.usage\"}},{\"id\":\"4\",\"enabled\":true,\"type\":\"terms\",\"schema\":\"group\",\"params\":{\"field\":\"stack_name\",\"size\":5,\"order\":\"desc\",\"orderBy\":\"3\"}}],\"listeners\":{}}",
      "uiStateJSON": "{}",
      "description": "",
      "version": 1,
      "kibanaSavedObjectMeta": {
        "searchSourceJSON": "{\"index\":\"ampbeat-*\",\"query\":{\"query_string\":{\"analyze_wildcard\":true,\"query\":\"*\"}},\"filter\":[]}"
      }
    }
  },
  {
    "_id": "a33ec3e0-1733-11e7-b973-af55f23595f6",
    "_type": "visualization",
    "_source": {
      "title": "mem_services",
      "visState": "{\"title\":\"mem_services\",\"type\":\"line\",\"params\":{\"addLegend\":true,\"addTimeMarker\":false,\"addTooltip\":true,\"defaultYExtents\":false,\"drawLinesBetweenPoints\":true,\"interpolate\":\"linear\",\"legendPosition\":\"right\",\"radiusRatio\":9,\"scale\":\"linear\",\"setYExtents\":false,\"showCircles\":true,\"times\":[]},\"aggs\":[{\"id\":\"2\",\"enabled\":true,\"type\":\"date_histogram\",\"schema\":\"segment\",\"params\":{\"field\":\"@timestamp\",\"interval\":\"auto\",\"customInterval\":\"2h\",\"min_doc_count\":1,\"extended_bounds\":{}}},{\"id\":\"3\",\"enabled\":true,\"type\":\"avg\",\"schema\":\"metric\",\"params\":{\"field\":\"mem.usage\"}},{\"id\":\"4\",\"enabled\":true,\"type\":\"terms\",\"schema\":\"group\",\"params\":{\"field\":\"service_name\",\"size\":5,\"order\":\"desc\",\"orderBy\":\"3\"}}],\"listeners\":{}}",
      "uiStateJSON": "{}",
      "description": "",
      "version": 1,
      "kibanaSavedObjectMeta": {
        "searchSourceJSON": "{\"index\":\"ampbeat-*\",\"query\":{\"query_string\":{\"analyze_wildcard\":true,\"query\":\"*\"}},\"filter\":[]}"
      }
    }
  },
  {
    "_id": "5791ca40-1734-11e7-b973-af55f23595f6",
    "_type": "visualization",
    "_source": {
      "title": "mem_stacks",
      "visState": "{\"title\":\"mem_stacks\",\"type\":\"line\",\"params\":{\"addLegend\":true,\"addTimeMarker\":false,\"addTooltip\":true,\"defaultYExtents\":false,\"drawLinesBetweenPoints\":true,\"interpolate\":\"linear\",\"legendPosition\":\"right\",\"radiusRatio\":9,\"scale\":\"linear\",\"setYExtents\":false,\"showCircles\":true,\"times\":[]},\"aggs\":[{\"id\":\"2\",\"enabled\":true,\"type\":\"date_histogram\",\"schema\":\"segment\",\"params\":{\"field\":\"@timestamp\",\"interval\":\"auto\",\"customInterval\":\"2h\",\"min_doc_count\":1,\"extended_bounds\":{}}},{\"id\":\"3\",\"enabled\":true,\"type\":\"avg\",\"schema\":\"metric\",\"params\":{\"field\":\"mem.usage\"}},{\"id\":\"4\",\"enabled\":true,\"type\":\"terms\",\"schema\":\"group\",\"params\":{\"field\":\"stack_name\",\"size\":5,\"order\":\"desc\",\"orderBy\":\"3\"}}],\"listeners\":{}}",
      "uiStateJSON": "{}",
      "description": "",
      "version": 1,
      "kibanaSavedObjectMeta": {
        "searchSourceJSON": "{\"index\":\"ampbeat-*\",\"query\":{\"query_string\":{\"analyze_wildcard\":true,\"query\":\"*\"}},\"filter\":[]}"
      }
    }
  }
]